materialize/__init__.py
materialize/components.enaml
materialize/fields.enaml
materialize/forms.enaml
materialize/page.enaml
materialize/utils.py
materialize_ui-0.1.19.dist-info/METADATA
materialize_ui-0.1.19.dist-info/WHEEL
materialize_ui-0.1.19.dist-info/top_level.txt
materialize_ui-0.1.19.dist-info/RECORD
