Metadata-Version: 2.1
Name: materialize-ui
Version: 0.1.19
Summary: Materailzie web components for enaml-web
Home-page: https://github.com/frmdstryr/materialize
Author: CodeLV
Author-email: frmdstryr@protonmail.com
License: MIT
Requires-Dist: enaml-web
